js_lib_dropzone/__init__.py
js_lib_dropzone/apps.py
js_lib_dropzone/static/js_lib_dropzone/basic.css
js_lib_dropzone/static/js_lib_dropzone/dropzone-amd-module.js
js_lib_dropzone/static/js_lib_dropzone/dropzone.css
js_lib_dropzone/static/js_lib_dropzone/dropzone.js
js_lib_dropzone/static/js_lib_dropzone/min/basic.min.css
js_lib_dropzone/static/js_lib_dropzone/min/dropzone-amd-module.min.js
js_lib_dropzone/static/js_lib_dropzone/min/dropzone.min.css
js_lib_dropzone/static/js_lib_dropzone/min/dropzone.min.js
django_js_lib_dropzone-5.9.3.1.dist-info/LICENSE
django_js_lib_dropzone-5.9.3.1.dist-info/WHEEL
django_js_lib_dropzone-5.9.3.1.dist-info/METADATA
django_js_lib_dropzone-5.9.3.1.dist-info/RECORD
