Metadata-Version: 2.3
Name: django-js-lib-dropzone
Version: 5.9.3.1
Summary: Dropzone.js Repackaged for Django
Classifier: License :: OSI Approved :: MIT License
